edwh_multipass_plugin/__about__.py
edwh_multipass_plugin/__init__.py
edwh_multipass_plugin/tasks.py
edwh_multipass_plugin-1.3.1.dist-info/METADATA
edwh_multipass_plugin-1.3.1.dist-info/WHEEL
edwh_multipass_plugin-1.3.1.dist-info/entry_points.txt
edwh_multipass_plugin-1.3.1.dist-info/RECORD
