Metadata-Version: 2.3
Name: edwh-multipass-plugin
Version: 1.3.1
Summary: An `edwh`plugin to work with multipass instances for local development.
Project-URL: Documentation, https://github.com/educationwarehouse/edwh-multipass-plugin#readme
Project-URL: Issues, https://github.com/educationwarehouse/edwh-multipass-plugin/issues
Project-URL: Source, https://github.com/educationwarehouse/edwh-multipass-plugin
Author-email: Remco <remco@educationwarehouse.nl>
Keywords: edwh,invoke,multipass,plugin
Classifier: Development Status :: 4 - Beta
Classifier: Programming Language :: Python
Classifier: Programming Language :: Python :: 3.10
Classifier: Programming Language :: Python :: 3.11
Classifier: Programming Language :: Python :: Implementation :: CPython
Classifier: Programming Language :: Python :: Implementation :: PyPy
Requires-Python: >=3.10
Requires-Dist: edwh>=0.53.7
Requires-Dist: pyyaml
Provides-Extra: dev
Requires-Dist: black; extra == 'dev'
Requires-Dist: hatch; extra == 'dev'
Requires-Dist: su6[all]; extra == 'dev'
Requires-Dist: types-pyyaml; extra == 'dev'
